logging_loki/__init__.py
logging_loki/const.py
logging_loki/emitter.py
logging_loki/handlers.py
python_logging_loki_v2-1.1.0.dist-info/licenses/LICENSE
python_logging_loki_v2-1.1.0.dist-info/METADATA
python_logging_loki_v2-1.1.0.dist-info/WHEEL
python_logging_loki_v2-1.1.0.dist-info/top_level.txt
python_logging_loki_v2-1.1.0.dist-info/RECORD
